agentworks/__init__.py
agentworks/config.py
agentworks/cost.py
agentworks/integrations/__init__.py
agentworks/integrations/langgraph.py
agentworks/otlp.py
agentworks/pii.py
agentworks/tracing.py
agentworks/utils.py
agentworks-0.1.2.dist-info/METADATA
agentworks-0.1.2.dist-info/WHEEL
agentworks-0.1.2.dist-info/RECORD
