Metadata-Version: 2.4
Name: agentworks
Version: 0.1.2
Summary: AgentWorks SDK - Instrument and observe multi-agent AI systems
License: MIT
Keywords: agents,observability,tracing,llm,ai
Author: AgentWorks Team
Requires-Python: >=3.10,<4.0
Classifier: Development Status :: 3 - Alpha
Classifier: Intended Audience :: Developers
Classifier: License :: OSI Approved :: MIT License
Classifier: Programming Language :: Python :: 3
Classifier: Programming Language :: Python :: 3.10
Classifier: Programming Language :: Python :: 3.11
Classifier: Programming Language :: Python :: 3.12
Classifier: Programming Language :: Python :: 3.13
Classifier: Programming Language :: Python :: 3.14
Requires-Dist: httpx (>=0.25.2,<0.26.0)
Requires-Dist: pydantic (>=2.5.0,<3.0.0)
Requires-Dist: pydantic-settings (>=2.1.0,<3.0.0)
Project-URL: Homepage, https://agentworks.dev
Project-URL: Repository, https://github.com/agentworks/agentworks
